django_assert_model_queries/__init__.py
django_assert_model_queries/patch.py
django_assert_model_queries/pytest.py
django_assert_model_queries/test.py
django_assert_model_queries-1.1.0.dist-info/METADATA
django_assert_model_queries-1.1.0.dist-info/WHEEL
django_assert_model_queries-1.1.0.dist-info/entry_points.txt
django_assert_model_queries-1.1.0.dist-info/licenses/LICENSE
django_assert_model_queries-1.1.0.dist-info/RECORD
