Metadata-Version: 2.3
Name: django-assert-model-queries
Version: 1.1.0
Summary: A Django test utility to assert the number of queries per model.
Project-URL: Changelog, https://github.com/aspiredu/django-assert-model-queries/blob/main/CHANGELOG.md
Project-URL: Homepage, https://github.com/aspiredu/django-assert-model-queries
Project-URL: Issues, https://github.com/aspiredu/django-assert-model-queries/issues
Author-email: Tim Schilling <tim@aspiredu.com>
Keywords: django,pytest,test
Classifier: Development Status :: 5 - Production/Stable
Classifier: Framework :: Django :: 4.2
Classifier: Framework :: Django :: 5.0
Classifier: Framework :: Django :: 5.1
Classifier: Framework :: Pytest
Classifier: Intended Audience :: Developers
Classifier: License :: OSI Approved :: MIT License
Classifier: Natural Language :: English
Classifier: Operating System :: OS Independent
Classifier: Programming Language :: Python :: 3 :: Only
Classifier: Programming Language :: Python :: 3.9
Classifier: Programming Language :: Python :: 3.10
Classifier: Programming Language :: Python :: 3.11
Classifier: Programming Language :: Python :: 3.12
Classifier: Programming Language :: Python :: 3.13
Classifier: Programming Language :: Python :: Implementation :: CPython
Requires-Python: >=3.9
Requires-Dist: django>=4.2
Provides-Extra: pytest
Requires-Dist: pytest-django; extra == 'pytest'
